pulumi_xenorchestra/__init__.py
pulumi_xenorchestra/_inputs.py
pulumi_xenorchestra/_utilities.py
pulumi_xenorchestra/acl.py
pulumi_xenorchestra/cloud_config.py
pulumi_xenorchestra/get_xoa_cloud_config.py
pulumi_xenorchestra/get_xoa_host.py
pulumi_xenorchestra/get_xoa_hosts.py
pulumi_xenorchestra/get_xoa_network.py
pulumi_xenorchestra/get_xoa_pif.py
pulumi_xenorchestra/get_xoa_pool.py
pulumi_xenorchestra/get_xoa_resource_set.py
pulumi_xenorchestra/get_xoa_storage_repository.py
pulumi_xenorchestra/get_xoa_template.py
pulumi_xenorchestra/get_xoa_user.py
pulumi_xenorchestra/get_xoa_vdi.py
pulumi_xenorchestra/get_xoa_vms.py
pulumi_xenorchestra/outputs.py
pulumi_xenorchestra/provider.py
pulumi_xenorchestra/pulumi-plugin.json
pulumi_xenorchestra/py.typed
pulumi_xenorchestra/resource_set.py
pulumi_xenorchestra/vdi.py
pulumi_xenorchestra/vm.py
pulumi_xenorchestra/xoa_bonded_network.py
pulumi_xenorchestra/xoa_network.py
pulumi_xenorchestra/config/__init__.py
pulumi_xenorchestra/config/__init__.pyi
pulumi_xenorchestra/config/vars.py
pulumi_xenorchestra-2.1.0.dist-info/METADATA
pulumi_xenorchestra-2.1.0.dist-info/WHEEL
pulumi_xenorchestra-2.1.0.dist-info/top_level.txt
pulumi_xenorchestra-2.1.0.dist-info/RECORD
